funml/__init__.py
funml/data/__init__.py
funml/data/enum.py
funml/data/lists.py
funml/data/monads.py
funml/data/records.py
funml/errors.py
funml/expressions.py
funml/json.py
funml/pattern_match.py
funml/pipeline.py
funml/types.py
funml/utils.py
funml-0.3.18.dist-info/LICENSE
funml-0.3.18.dist-info/METADATA
funml-0.3.18.dist-info/WHEEL
funml-0.3.18.dist-info/RECORD
