Metadata-Version: 2.1
Name: funml
Version: 0.3.18
Summary: A collection of utilities to help write python as though it were an ML-kind of functional language like OCaml
Home-page: https://github.com/sopherapps/funml
License: MIT
Keywords: functional-programming,ml,piping
Author: Martin
Author-email: team.sopherapps@gmail.com
Requires-Python: >=3.7,<4.0
Classifier: License :: OSI Approved :: MIT License
Classifier: Programming Language :: Python :: 3
Classifier: Programming Language :: Python :: 3.7
Classifier: Programming Language :: Python :: 3.8
Classifier: Programming Language :: Python :: 3.9
Classifier: Programming Language :: Python :: 3.10
Classifier: Programming Language :: Python :: 3.11
Requires-Dist: typing-extensions (>=4.4.0,<5.0.0)
Project-URL: Documentation, https://sopherapps.github.io/funml
Project-URL: Repository, https://github.com/sopherapps/funml
